mosqlient/__init__.py
mosqlient/__main__.py
mosqlient/_config/__init__.py
mosqlient/_config/globals.py
mosqlient/_utils/__init__.py
mosqlient/_utils/brasil.py
mosqlient/cli.py
mosqlient/client.py
mosqlient/datastore/__init__.py
mosqlient/datastore/_climate_get_impl.py
mosqlient/datastore/_episcanner_get_impl.py
mosqlient/datastore/_infodengue_get_impl.py
mosqlient/datastore/_mosquito_get_impl.py
mosqlient/datastore/models.py
mosqlient/datastore/schema.py
mosqlient/errors.py
mosqlient/forecast/__init__.py
mosqlient/forecast/baseline.py
mosqlient/forecast/ensemble.py
mosqlient/forecast/viz.py
mosqlient/prediction_optimize/__init__.py
mosqlient/prediction_optimize/pred_opt.py
mosqlient/registry/__init__.py
mosqlient/registry/_author_get_impl.py
mosqlient/registry/_model_delete_impl.py
mosqlient/registry/_model_get_impl.py
mosqlient/registry/_model_post_impl.py
mosqlient/registry/_prediction_delete_impl.py
mosqlient/registry/_prediction_get_impl.py
mosqlient/registry/_prediction_post_impl.py
mosqlient/registry/models.py
mosqlient/registry/schema.py
mosqlient/scoring/__init__.py
mosqlient/scoring/score.py
mosqlient/tests/__init__.py
mosqlient/types.py
mosqlient/validations.py
mosqlient-1.9.3.dist-info/LICENSE
mosqlient-1.9.3.dist-info/METADATA
mosqlient-1.9.3.dist-info/WHEEL
mosqlient-1.9.3.dist-info/entry_points.txt
mosqlient-1.9.3.dist-info/RECORD
