Metadata-Version: 2.3
Name: mosqlient
Version: 1.9.3
Summary: client library for the mosqlimate client library
License: GPLv3
Keywords: data science,epidemiology,forecasting
Author: Flávio Codeço Coelho
Author-email: fccoelho@gmail.com
Requires-Python: >=3.10,<3.13
Classifier: License :: Other/Proprietary License
Classifier: Programming Language :: Python :: 3
Classifier: Programming Language :: Python :: 3.10
Classifier: Programming Language :: Python :: 3.11
Classifier: Programming Language :: Python :: 3.12
Provides-Extra: analyze
Requires-Dist: aiohttp (>=3.9.5,<4.0.0)
Requires-Dist: altair (>=5.3.0,<6.0.0) ; extra == "analyze"
Requires-Dist: cffi (>=1.17.0,<2.0.0)
Requires-Dist: epiweeks (>=2.3.0,<3.0.0) ; extra == "analyze"
Requires-Dist: loguru (>=0.7.3,<0.8.0)
Requires-Dist: matplotlib (>=3.9.0,<4.0.0) ; extra == "analyze"
Requires-Dist: nest-asyncio (>=1.6.0,<2.0.0)
Requires-Dist: pandas (>=2.2.2,<3.0.0)
Requires-Dist: pmdarima (>=2.0.4,<3.0.0) ; extra == "analyze"
Requires-Dist: pydantic (>=2.7.3,<3.0.0)
Requires-Dist: requests (>=2.32.2,<3.0.0)
Requires-Dist: scikit-learn (>=1.5.0,<2.0.0) ; extra == "analyze"
Requires-Dist: scoringrules (>=0.5.2,<0.6.0) ; extra == "analyze"
Requires-Dist: tabulate (>=0.9.0,<0.10.0)
Requires-Dist: tqdm (>=4.67.1,<5.0.0)
Requires-Dist: types-requests (>=2.32.0.20240523,<3.0.0.0)
Requires-Dist: vl-convert-python (>=1.7.0,<2.0.0)
Project-URL: Homepage, https://github.com/Mosqlimate-project/mosqlimate-client
Project-URL: Repository, https://github.com/Mosqlimate-project/mosqlimate-client
